dpnp/__init__.py
dpnp/_version.py
dpnp/config.py
dpnp/dpnp_array.py
dpnp/dpnp_array_api_info.py
dpnp/dpnp_container.py
dpnp/dpnp_flatiter.py
dpnp/dpnp_iface.py
dpnp/dpnp_iface_arraycreation.py
dpnp/dpnp_iface_bitwise.py
dpnp/dpnp_iface_counting.py
dpnp/dpnp_iface_functional.py
dpnp/dpnp_iface_histograms.py
dpnp/dpnp_iface_indexing.py
dpnp/dpnp_iface_linearalgebra.py
dpnp/dpnp_iface_logic.py
dpnp/dpnp_iface_manipulation.py
dpnp/dpnp_iface_mathematical.py
dpnp/dpnp_iface_nanfunctions.py
dpnp/dpnp_iface_searching.py
dpnp/dpnp_iface_sorting.py
dpnp/dpnp_iface_statistics.py
dpnp/dpnp_iface_trigonometric.py
dpnp/dpnp_iface_types.py
dpnp/dpnp_iface_utils.py
dpnp/dpnp_iface_window.py
dpnp/libdpnp_backend_c.so
dpnp/backend/extensions/blas/_blas_impl.cpython-312-x86_64-linux-gnu.so
dpnp/backend/extensions/fft/_fft_impl.cpython-312-x86_64-linux-gnu.so
dpnp/backend/extensions/indexing/_indexing_impl.cpython-312-x86_64-linux-gnu.so
dpnp/backend/extensions/lapack/_lapack_impl.cpython-312-x86_64-linux-gnu.so
dpnp/backend/extensions/statistics/_statistics_impl.cpython-312-x86_64-linux-gnu.so
dpnp/backend/extensions/ufunc/_ufunc_impl.cpython-312-x86_64-linux-gnu.so
dpnp/backend/extensions/vm/_vm_impl.cpython-312-x86_64-linux-gnu.so
dpnp/backend/extensions/window/_window_impl.cpython-312-x86_64-linux-gnu.so
dpnp/backend/include/dpnp_iface.hpp
dpnp/backend/include/dpnp_iface_fptr.hpp
dpnp/backend/include/dpnp_iface_random.hpp
dpnp/dpnp_algo/__init__.py
dpnp/dpnp_algo/dpnp_algo.cpython-312-x86_64-linux-gnu.so
dpnp/dpnp_algo/dpnp_arraycreation.py
dpnp/dpnp_algo/dpnp_elementwise_common.py
dpnp/dpnp_algo/dpnp_fill.py
dpnp/dpnp_utils/__init__.py
dpnp/dpnp_utils/dpnp_algo_utils.cpython-312-x86_64-linux-gnu.so
dpnp/dpnp_utils/dpnp_utils_common.py
dpnp/dpnp_utils/dpnp_utils_einsum.py
dpnp/dpnp_utils/dpnp_utils_linearalgebra.py
dpnp/dpnp_utils/dpnp_utils_pad.py
dpnp/dpnp_utils/dpnp_utils_reduction.py
dpnp/dpnp_utils/dpnp_utils_statistics.py
dpnp/fft/__init__.py
dpnp/fft/dpnp_iface_fft.py
dpnp-0.19.1.dist-info/licenses/LICENSE.txt
dpnp-0.19.1.dist-info/METADATA
dpnp-0.19.1.dist-info/WHEEL
dpnp-0.19.1.dist-info/top_level.txt
dpnp-0.19.1.dist-info/RECORD
