Metadata-Version: 2.4
Name: dpnp
Version: 0.19.1
Summary: Data Parallel Extension for NumPy
Author: Intel Corporation
Maintainer: Intel Corporation
License-Expression: BSD-2-Clause
Project-URL: Changelog, https://github.com/IntelPython/dpnp/blob/master/CHANGELOG.md
Project-URL: Documentation, https://intelpython.github.io/dpnp
Project-URL: Homepage, https://github.com/IntelPython/dpnp
Project-URL: Issues, https://github.com/IntelPython/dpnp/issues
Project-URL: Repository, https://github.com/IntelPython/dpnp.git
Keywords: dpnp,sycl,numpy,python3,intel,mkl,oneapi,gpu,dpcpp
Classifier: Development Status :: 4 - Beta
Classifier: Intended Audience :: Science/Research
Classifier: Intended Audience :: Developers
Classifier: Programming Language :: C++
Classifier: Programming Language :: Cython
Classifier: Programming Language :: Python
Classifier: Programming Language :: Python :: 3
Classifier: Programming Language :: Python :: 3.9
Classifier: Programming Language :: Python :: 3.10
Classifier: Programming Language :: Python :: 3.11
Classifier: Programming Language :: Python :: 3.12
Classifier: Programming Language :: Python :: 3.13
Classifier: Programming Language :: Python :: 3.14
Classifier: Programming Language :: Python :: 3 :: Only
Classifier: Programming Language :: Python :: Implementation :: CPython
Classifier: Topic :: Software Development
Classifier: Topic :: Scientific/Engineering
Classifier: Operating System :: Microsoft :: Windows
Classifier: Operating System :: POSIX :: Linux
Classifier: Operating System :: POSIX
Classifier: Operating System :: Unix
Requires-Python: <3.15,>=3.9
License-File: LICENSE.txt
Provides-Extra: coverage
Provides-Extra: docs
Provides-Extra: test
Dynamic: license-file
Requires-Dist: dpcpp-cpp-rt >=2025.3,<2026.0a0
Requires-Dist: dpctl >=0.21.1
Requires-Dist: numpy
Requires-Dist: onemkl-sycl-blas >=2025.3,<2026.0a0
Requires-Dist: onemkl-sycl-dft >=2025.3,<2026.0a0
Requires-Dist: onemkl-sycl-lapack >=2025.3,<2026.0a0
Requires-Dist: onemkl-sycl-rng >=2025.3,<2026.0a0
Requires-Dist: onemkl-sycl-stats >=2025.3,<2026.0a0
Requires-Dist: onemkl-sycl-vm >=2025.3,<2026.0a0
